<?xml version="1.0" encoding="UTF-8"?>
<launch4jConfig>
  <dontWrapJar>false</dontWrapJar>
  <headerType>gui</headerType>
  <jar>C:\Users\user\Desktop\hello\src\src.jar</jar>
  <outfile>C:\Users\user\Desktop\sample.exe</outfile>
  <errTitle>SimpleApp</errTitle>
  <cmdLine></cmdLine>
  <chdir>.</chdir>
  <priority>normal</priority>
  <downloadUrl>http://java.com/download</downloadUrl>
  <supportUrl></supportUrl>
  <stayAlive>false</stayAlive>
  <restartOnCrash>false</restartOnCrash>
  <manifest></manifest>
  <icon>C:\Users\user\Desktop\simple.jpg</icon>
  <jre>
    <path>%JAVA_HOME%;%PATH%</path>
    <requiresJdk>true</requiresJdk>
    <requires64Bit>true</requires64Bit>
    <minVersion>8</minVersion>
    <maxVersion></maxVersion>
  </jre>
</launch4jConfig>